add_command_dialog.py
command.py
context_formatter.py
debug_logger.py
feedback_config.py
feedback_ui.py
get_session_id.py
git_operations.py
ide_utils.py
path_config.py
post_task_hook.py
record.py
server.py
session_manager.py
stop_hook.py
window_position_manager.py
workspace_manager.py
components/__init__.py
components/agent_popup.py
components/chat_history.py
components/command_popup.py
components/feedback_text_edit.py
components/file_popup.py
components/history_popup.py
components/markdown_display.py
tabs/__init__.py
tabs/base_tab.py
tabs/chat_history_style.qss
tabs/chat_history_tab.py
tabs/chat_tab.py
tabs/workspace_tab.py
ui/__init__.py
ui/__main__.py
ui/compact_feedback_ui.py
ui/session_list_ui.py
ui/styles/session_list.qss
feedback_mcp-1.0.78.dist-info/METADATA
feedback_mcp-1.0.78.dist-info/WHEEL
feedback_mcp-1.0.78.dist-info/entry_points.txt
feedback_mcp-1.0.78.dist-info/top_level.txt
feedback_mcp-1.0.78.dist-info/RECORD
