Metadata-Version: 2.4
Name: feedback-mcp
Version: 1.0.78
Summary: Interactive Feedback MCP Server with UI - 支持工作空间管理、任务追踪、检查点恢复的反馈系统
Author-email: Yang <your.email@example.com>
License-Expression: MIT
Project-URL: Homepage, https://github.com/yourusername/feedback-mcp
Project-URL: Repository, https://github.com/yourusername/feedback-mcp
Project-URL: Issues, https://github.com/yourusername/feedback-mcp/issues
Keywords: mcp,feedback,interactive,workspace,task-management,checkpoint,ai-assistant,development-tools
Classifier: Development Status :: 4 - Beta
Classifier: Intended Audience :: Developers
Classifier: Programming Language :: Python :: 3
Classifier: Programming Language :: Python :: 3.10
Classifier: Programming Language :: Python :: 3.11
Classifier: Programming Language :: Python :: 3.12
Classifier: Topic :: Software Development :: Libraries :: Python Modules
Classifier: Topic :: Software Development :: User Interfaces
Classifier: Operating System :: OS Independent
Requires-Python: >=3.10
Requires-Dist: fastmcp==2.5.1
Requires-Dist: PySide6<7.0.0,>=6.8.0
Requires-Dist: psutil<8.0.0,>=6.0.0
Requires-Dist: markdown<4.0.0,>=3.6
Requires-Dist: pyyaml<7.0.0,>=6.0.0
Requires-Dist: requests<3.0.0,>=2.28.0
Requires-Dist: python-dotenv<2.0.0,>=1.0.0
Requires-Dist: urllib3<3.0.0,>=2.0.0
Requires-Dist: websockets==15.0.1
Requires-Dist: Pillow<12.0.0,>=10.0.0
Requires-Dist: pyperclip<2.0.0,>=1.8.0
Provides-Extra: dev
Requires-Dist: pytest; extra == "dev"
Requires-Dist: black; extra == "dev"
Requires-Dist: flake8; extra == "dev"
Requires-Dist: build; extra == "dev"
Requires-Dist: twine; extra == "dev"
